torch_accel/__init__.py
torch_accel/amp.py
torch_accel/ddp.py
torch_accel-0.1.1.dist-info/WHEEL
torch_accel-0.1.1.dist-info/METADATA
torch_accel-0.1.1.dist-info/RECORD
